{
    "parameterSets": {
        "ganimedes hero": {
            "__BallClipCount": "1",
            "__BallClipEnabled": "true",
            "__BallClipInset": "77",
            "__BallClipSize": "50",
            "__CardStackSize": "[37, 46, 42]",
            "__CornerBottomPercent": "20",
            "__CornerUpperPercent": "30",
            "__DisplayCardStack": "true",
            "__DisplayCorners": "true",
            "__DisplayFloor": "true",
            "__DisplayOnlyOneCorner": "false",
            "__DisplayOnlyOneWall": "false",
            "__DisplayRoof": "true",
            "__DisplayWalls": "true",
            "__EmptySpaceMargin": "1",
            "__IsRounded": "true",
            "__MagnetCountX": "1",
            "__MagnetCountY": "1",
            "__MagnetHeight": "2",
            "__MagnetRadius": "1.5",
            "__MagnetsEnabled": "true",
            "__PartsHorizontalSeparation": "10",
            "__PartsVerticalSeparation": "20",
            "__RoundingRadiusPercent": "15",
            "__Roundness": "0",
            "__SideBySide": "X",
            "__SlopedBezels": "true",
            "__WallThickness": "4"
        },
        "Terraformin Mars 60mm jacketed stack": {
            "__BallClipCount": "2",
            "__BallClipEnabled": "true",
            "__BallClipInset": "75",
            "__BallClipSize": "50",
            "__CardStackSize": "[70, 93, 60]",
            "__CornerBottomPercent": "20",
            "__CornerUpperPercent": "30",
            "__DisplayCardStack": "true",
            "__DisplayCorners": "true",
            "__DisplayFloor": "true",
            "__DisplayOnlyOneCorner": "false",
            "__DisplayOnlyOneWall": "false",
            "__DisplayRoof": "true",
            "__DisplayWalls": "true",
            "__EmptySpaceMargin": "0",
            "__IsRounded": "true",
            "__MagnetCountX": "2",
            "__MagnetCountY": "3",
            "__MagnetHeight": "2",
            "__MagnetRadius": "1.5",
            "__MagnetsEnabled": "true",
            "__PartsHorizontalSeparation": "5",
            "__PartsVerticalSeparation": "20",
            "__PegConnectorsEnabled": "true",
            "__PegConnectorsHeight": "50",
            "__PegConnectorsOnSides": "true",
            "__PegConnectorsPerCorner": "3",
            "__PegConnectorsPerWallX": "2",
            "__PegConnectorsPerWallY": "3",
            "__PegConnectorsSize": "50",
            "__RoundingRadiusPercent": "15",
            "__Roundness": "0",
            "__SideBySide": "false",
            "__SlopedBezels": "true",
            "__WallThickness": "5",
            "__WallVerticalSeparation": "18"
        }
    },
    "fileFormatVersion": "1",
    "parameterSets": "",
    "parameterSets": ""
}
